immutableType/Bool.py
immutableType/Callable.py
immutableType/Dict.py
immutableType/Float.py
immutableType/Int.py
immutableType/List.py
immutableType/Set.py
immutableType/Str.py
immutableType/Subclass.py
immutableType/Tuple.py
immutableType/__init__.py
immutableType/_convert_mutable.py
immutableType/_error.py
immutable_python_type-1.2.3.dist-info/licenses/LICENSE
immutable_python_type-1.2.3.dist-info/METADATA
immutable_python_type-1.2.3.dist-info/WHEEL
immutable_python_type-1.2.3.dist-info/top_level.txt
immutable_python_type-1.2.3.dist-info/RECORD
