Metadata-Version: 2.4
Name: immutable-Python-Type
Version: 1.2.3
Summary: A immutable type for Python
Home-page: https://github.com/BOXERRMD/immutable
Author: BOXER
Author-email: vagabonwalybi@gmail.com
Maintainer: BOXER
Maintainer-email: vagabonwalybi@gmail.com
Project-URL: Documentation, https://github.com/BOXERRMD/immutable/wiki
Project-URL: GitHub, https://github.com/BOXERRMD/immutable
Classifier: Programming Language :: Python :: 3.11
Classifier: Natural Language :: English
Classifier: Operating System :: Microsoft :: Windows :: Windows 11
Classifier: Operating System :: Microsoft :: Windows :: Windows 10
Requires-Python: >=3.9
License-File: LICENSE
Dynamic: author
Dynamic: author-email
Dynamic: classifier
Dynamic: description
Dynamic: description-content-type
Dynamic: home-page
Dynamic: license-file
Dynamic: maintainer
Dynamic: maintainer-email
Dynamic: project-url
Dynamic: requires-python
Dynamic: summary
